pepdocs/__init__.py
pepdocs/__main__.py
pepdocs/_pepdocs.py
pepdocs/config/__init__.py
pepdocs/config/pepdocs.toml
pepdocs-0.3.0.dist-info/entry_points.txt
pepdocs-0.3.0.dist-info/LICENSE
pepdocs-0.3.0.dist-info/WHEEL
pepdocs-0.3.0.dist-info/METADATA
pepdocs-0.3.0.dist-info/RECORD
