Metadata-Version: 2.1
Name: pepdocs
Version: 0.3.0
Summary: PepDocs, read PEPs in your console
Home-page: https://github.com/gahjelle/pepdocs
Keywords: pep
Author: Geir Arne Hjelle
Author-email: geirarne@gmail.com
Requires-Python: >=3.8
Classifier: Development Status :: 2 - Pre-Alpha
Classifier: Environment :: Console
Classifier: Intended Audience :: Developers
Classifier: License :: OSI Approved :: MIT License
Classifier: Natural Language :: English
Classifier: Operating System :: MacOS
Classifier: Operating System :: Microsoft
Classifier: Operating System :: POSIX :: Linux
Classifier: Programming Language :: Python :: 3.8
Classifier: Programming Language :: Python :: 3.9
Classifier: Programming Language :: Python :: 3.10
Classifier: Topic :: Documentation
Classifier: Topic :: Software Development :: Documentation
Requires-Dist: pyconfs[toml]
Requires-Dist: requests
Requires-Dist: rst-to-myst
Requires-Dist: typer
Requires-Dist: black ; extra == "dev"
Requires-Dist: bumpversion ; extra == "dev"
Requires-Dist: flake8 ; extra == "dev"
Requires-Dist: flit ; extra == "dev"
Requires-Dist: interrogate ; extra == "dev"
Requires-Dist: isort ; extra == "dev"
Requires-Dist: mypy ; extra == "dev"
Requires-Dist: pre-commit ; extra == "dev"
Requires-Dist: mkdocs ; extra == "doc"
Requires-Dist: black ; extra == "test"
Requires-Dist: flake8 ; extra == "test"
Requires-Dist: interrogate ; extra == "test"
Requires-Dist: isort ; extra == "test"
Requires-Dist: mypy ; extra == "test"
Requires-Dist: pytest ; extra == "test"
Requires-Dist: pytest-cov ; extra == "test"
Requires-Dist: tox ; extra == "test"
Provides-Extra: dev
Provides-Extra: doc
Provides-Extra: test
